{
  "name": "Lácteos y quesos",
  "category": "Prohibido / Lácteos",
  "status": "danger",
  "instructions": "La leche, el yogur y las orillas de queso están estrictamente prohibidos. Las grasas y proteínas lácteas de difícil asimilación causan una veloz descomposición anaeróbica, liberando ácidos orgánicos agresivos y malos olores fétidos. Atraen moscas domésticas y roedores al contenedor. Además, la acidez extrema quema la piel de las lombrices.",
  "nutrition": "Aportan Calcio (Ca) y Fósforo (P), pero los efectos destructivos de la anaerobiosis y la acidez del ácido láctico descartan por completo su uso.",
  "keywords": "queso, orillas de queso, leche, yogur, yogurt, lacteos, lactosa, crema"
}
